bian-0.1.0.dist-info/METADATA
bian-0.1.0.dist-info/WHEEL
bian/__init__.py
bian-0.1.0.dist-info/RECORD
