Metadata-Version: 2.1
Name: bian
Version: 0.1.0
Summary: Default template for PDM package
Author-Email: Meng Xiangzhuo <aumo@foxmail.com>
License: MIT
Requires-Python: >=3.12
Requires-Dist: pandas>=2.2.2
Requires-Dist: python-binance>=1.0.19
